README.rst
setup.py
phuntic/__init__.py
phuntic/tests.py
phuntic.egg-info/PKG-INFO
phuntic.egg-info/SOURCES.txt
phuntic.egg-info/dependency_links.txt
phuntic.egg-info/top_level.txt