Metadata-Version: 1.0
Name: phuntic
Version: 0.1.3
Summary: Python Object Serializer (JSON wrapper)
Home-page: https://github.com/kidig/phuntic
Author: Dmitrii Gerasimenko
Author-email: kiddima@gmail.com
License: UNKNOWN
Platform: UNKNOWN
